{
  "countryCode": "ethiopia",
  "updatedAt": "2026-03-27T21:38:37.385Z",
  "users": [],
  "rankings": {
    "public_contributions": [
      {
        "login": "eth-dev-1",
        "avatarUrl": "https://avatars.githubusercontent.com/u/42000?v=4",
        "name": "Dev 1 (Ethiopia)",
        "company": "Google",
        "location": "Addis ababa",
        "bio": "Developer from Ethiopia",
        "followers": 5010,
        "publicContributions": 35056,
        "privateContributions": 352,
        "languages": ["Kotlin", "Java"],
        "topRepos": [
          {
            "name": "eth-dev-1-proj-1",
            "description": null,
            "stars": 35,
            "language": "Kotlin"
          },
          {
            "name": "eth-dev-1-proj-2",
            "description": "Open source utilities",
            "stars": 1156,
            "language": "Java"
          }
        ],
        "twitterUsername": "eth-dev-1",
        "blog": "https://eth-dev-1.dev"
      },
      {
        "login": "eth-dev-2",
        "avatarUrl": "https://avatars.githubusercontent.com/u/42001?v=4",
        "name": "Dev 2 (Ethiopia)",
        "company": "Microsoft",
        "location": "Ethiopia",
        "bio": "Developer from Ethiopia",
        "followers": 4837,
        "publicContributions": 33756,
        "privateContributions": 362,
        "languages": ["TypeScript", "Python"],
        "topRepos": [
          {
            "name": "eth-dev-2-proj-1",
            "description": "Web framework for developers",
            "stars": 1879,
            "language": "TypeScript"
          },
          {
            "name": "eth-dev-2-proj-2",
            "description": "Data pipeline library",
            "stars": 1368,
            "language": "Python"
          }
        ],
        "twitterUsername": "eth-dev-2",
        "blog": null
      },
      {
        "login": "eth-dev-3",
        "avatarUrl": "https://avatars.githubusercontent.com/u/42002?v=4",
        "name": "Dev 3 (Ethiopia)",
        "company": "Apple",
        "location": "Ethiopia",
        "bio": "Developer from Ethiopia",
        "followers": 4659,
        "publicContributions": 32392,
        "privateContributions": 240,
        "languages": ["Swift"],
        "topRepos": [
          {
            "name": "eth-dev-3-proj-1",
            "description": "Data pipeline library",
            "stars": 1131,
            "language": "Swift"
          },
          {
            "name": "eth-dev-3-proj-2",
            "description": "Open source utilities",
            "stars": 397,
            "language": "Swift"
          }
        ],
        "twitterUsername": null,
        "blog": null
      },
      {
        "login": "eth-dev-4",
        "avatarUrl": "https://avatars.githubusercontent.com/u/42003?v=4",
        "name": "Dev 4 (Ethiopia)",
        "company": "Amazon",
        "location": "Ethiopia",
        "bio": null,
        "followers": 4452,
        "publicContributions": 31181,
        "privateContributions": 202,
        "languages": ["Java", "Go", "C++", "Swift"],
        "topRepos": [
          {
            "name": "eth-dev-4-proj-1",
            "description": "A modern CLI tool",
            "stars": 1216,
            "language": "Java"
          },
          {
            "name": "eth-dev-4-proj-2",
            "description": "Data pipeline library",
            "stars": 595,
            "language": "Go"
          },
          {
            "name": "eth-dev-4-proj-3",
            "description": "Web framework for developers",
            "stars": 598,
            "language": "C++"
          }
        ],
        "twitterUsername": null,
        "blog": null
      },
      {
        "login": "eth-dev-5",
        "avatarUrl": "https://avatars.githubusercontent.com/u/42004?v=4",
        "name": "Dev 5 (Ethiopia)",
        "company": null,
        "location": "Addis ababa",
        "bio": null,
        "followers": 4277,
        "publicContributions": 30001,
        "privateContributions": 258,
        "languages": ["Java", "Python", "Rust"],
        "topRepos": [
          {
            "name": "eth-dev-5-proj-1",
            "description": "Open source utilities",
            "stars": 997,
            "language": "Java"
          },
          {
            "name": "eth-dev-5-proj-2",
            "description": null,
            "stars": 877,
            "language": "Python"
          }
        ],
        "twitterUsername": null,
        "blog": null
      },
      {
        "login": "eth-dev-6",
        "avatarUrl": "https://avatars.githubusercontent.com/u/42005?v=4",
        "name": "Dev 6 (Ethiopia)",
        "company": "GitHub",
        "location": "Ethiopia",
        "bio": null,
        "followers": 4105,
        "publicContributions": 28812,
        "privateContributions": 205,
        "languages": ["JavaScript"],
        "topRepos": [
          {
            "name": "eth-dev-6-proj-1",
            "description": null,
            "stars": 987,
            "language": "JavaScript"
          },
          {
            "name": "eth-dev-6-proj-2",
            "description": "API wrapper",
            "stars": 1142,
            "language": "JavaScript"
          }
        ],
        "twitterUsername": null,
        "blog": null
      },
      {
        "login": "eth-dev-7",
        "avatarUrl": "https://avatars.githubusercontent.com/u/42006?v=4",
        "name": "Dev 7 (Ethiopia)",
        "company": "Amazon",
        "location": "Ethiopia",
        "bio": null,
        "followers": 3962,
        "publicContributions": 27624,
        "privateContributions": 273,
        "languages": ["Rust"],
        "topRepos": [
          {
            "name": "eth-dev-7-proj-1",
            "description": "Data pipeline library",
            "stars": 568,
            "language": "Rust"
          },
          {
            "name": "eth-dev-7-proj-2",
            "description": "Open source utilities",
            "stars": 864,
            "language": "Rust"
          },
          {
            "name": "eth-dev-7-proj-3",
            "description": "API wrapper",
            "stars": 1333,
            "language": "Rust"
          }
        ],
        "twitterUsername": null,
        "blog": null
      },
      {
        "login": "eth-dev-8",
        "avatarUrl": "https://avatars.githubusercontent.com/u/42007?v=4",
        "name": "Dev 8 (Ethiopia)",
        "company": null,
        "location": "Addis ababa",
        "bio": null,
        "followers": 3803,
        "publicContributions": 26608,
        "privateContributions": 324,
        "languages": ["Go"],
        "topRepos": [
          {
            "name": "eth-dev-8-proj-1",
            "description": "A modern CLI tool",
            "stars": 1177,
            "language": "Go"
          },
          {
            "name": "eth-dev-8-proj-2",
            "description": "A modern CLI tool",
            "stars": 573,
            "language": "Go"
          }
        ],
        "twitterUsername": null,
        "blog": null
      },
      {
        "login": "eth-dev-9",
        "avatarUrl": "https://avatars.githubusercontent.com/u/42008?v=4",
        "name": "Dev 9 (Ethiopia)",
        "company": "Stripe",
        "location": "Ethiopia",
        "bio": null,
        "followers": 3663,
        "publicContributions": 25489,
        "privateContributions": 70,
        "languages": ["TypeScript", "JavaScript", "Python", "PHP"],
        "topRepos": [
          {
            "name": "eth-dev-9-proj-1",
            "description": null,
            "stars": 458,
            "language": "TypeScript"
          },
          {
            "name": "eth-dev-9-proj-2",
            "description": "Open source utilities",
            "stars": 256,
            "language": "JavaScript"
          }
        ],
        "twitterUsername": null,
        "blog": null
      },
      {
        "login": "eth-dev-10",
        "avatarUrl": "https://avatars.githubusercontent.com/u/42009?v=4",
        "name": "Dev 10 (Ethiopia)",
        "company": "Google",
        "location": "Ethiopia",
        "bio": null,
        "followers": 3512,
        "publicContributions": 24516,
        "privateContributions": 422,
        "languages": ["Go"],
        "topRepos": [
          {
            "name": "eth-dev-10-proj-1",
            "description": null,
            "stars": 928,
            "language": "Go"
          }
        ],
        "twitterUsername": null,
        "blog": null
      }
    ],
    "total_contributions": [
      {
        "login": "eth-dev-1",
        "avatarUrl": "https://avatars.githubusercontent.com/u/42000?v=4",
        "name": "Dev 1 (Ethiopia)",
        "company": "Google",
        "location": "Addis ababa",
        "bio": "Developer from Ethiopia",
        "followers": 5010,
        "publicContributions": 35056,
        "privateContributions": 352,
        "languages": ["Kotlin", "Java"],
        "topRepos": [
          {
            "name": "eth-dev-1-proj-1",
            "description": null,
            "stars": 35,
            "language": "Kotlin"
          },
          {
            "name": "eth-dev-1-proj-2",
            "description": "Open source utilities",
            "stars": 1156,
            "language": "Java"
          }
        ],
        "twitterUsername": "eth-dev-1",
        "blog": "https://eth-dev-1.dev"
      },
      {
        "login": "eth-dev-2",
        "avatarUrl": "https://avatars.githubusercontent.com/u/42001?v=4",
        "name": "Dev 2 (Ethiopia)",
        "company": "Microsoft",
        "location": "Ethiopia",
        "bio": "Developer from Ethiopia",
        "followers": 4837,
        "publicContributions": 33756,
        "privateContributions": 362,
        "languages": ["TypeScript", "Python"],
        "topRepos": [
          {
            "name": "eth-dev-2-proj-1",
            "description": "Web framework for developers",
            "stars": 1879,
            "language": "TypeScript"
          },
          {
            "name": "eth-dev-2-proj-2",
            "description": "Data pipeline library",
            "stars": 1368,
            "language": "Python"
          }
        ],
        "twitterUsername": "eth-dev-2",
        "blog": null
      },
      {
        "login": "eth-dev-3",
        "avatarUrl": "https://avatars.githubusercontent.com/u/42002?v=4",
        "name": "Dev 3 (Ethiopia)",
        "company": "Apple",
        "location": "Ethiopia",
        "bio": "Developer from Ethiopia",
        "followers": 4659,
        "publicContributions": 32392,
        "privateContributions": 240,
        "languages": ["Swift"],
        "topRepos": [
          {
            "name": "eth-dev-3-proj-1",
            "description": "Data pipeline library",
            "stars": 1131,
            "language": "Swift"
          },
          {
            "name": "eth-dev-3-proj-2",
            "description": "Open source utilities",
            "stars": 397,
            "language": "Swift"
          }
        ],
        "twitterUsername": null,
        "blog": null
      },
      {
        "login": "eth-dev-4",
        "avatarUrl": "https://avatars.githubusercontent.com/u/42003?v=4",
        "name": "Dev 4 (Ethiopia)",
        "company": "Amazon",
        "location": "Ethiopia",
        "bio": null,
        "followers": 4452,
        "publicContributions": 31181,
        "privateContributions": 202,
        "languages": ["Java", "Go", "C++", "Swift"],
        "topRepos": [
          {
            "name": "eth-dev-4-proj-1",
            "description": "A modern CLI tool",
            "stars": 1216,
            "language": "Java"
          },
          {
            "name": "eth-dev-4-proj-2",
            "description": "Data pipeline library",
            "stars": 595,
            "language": "Go"
          },
          {
            "name": "eth-dev-4-proj-3",
            "description": "Web framework for developers",
            "stars": 598,
            "language": "C++"
          }
        ],
        "twitterUsername": null,
        "blog": null
      },
      {
        "login": "eth-dev-5",
        "avatarUrl": "https://avatars.githubusercontent.com/u/42004?v=4",
        "name": "Dev 5 (Ethiopia)",
        "company": null,
        "location": "Addis ababa",
        "bio": null,
        "followers": 4277,
        "publicContributions": 30001,
        "privateContributions": 258,
        "languages": ["Java", "Python", "Rust"],
        "topRepos": [
          {
            "name": "eth-dev-5-proj-1",
            "description": "Open source utilities",
            "stars": 997,
            "language": "Java"
          },
          {
            "name": "eth-dev-5-proj-2",
            "description": null,
            "stars": 877,
            "language": "Python"
          }
        ],
        "twitterUsername": null,
        "blog": null
      },
      {
        "login": "eth-dev-6",
        "avatarUrl": "https://avatars.githubusercontent.com/u/42005?v=4",
        "name": "Dev 6 (Ethiopia)",
        "company": "GitHub",
        "location": "Ethiopia",
        "bio": null,
        "followers": 4105,
        "publicContributions": 28812,
        "privateContributions": 205,
        "languages": ["JavaScript"],
        "topRepos": [
          {
            "name": "eth-dev-6-proj-1",
            "description": null,
            "stars": 987,
            "language": "JavaScript"
          },
          {
            "name": "eth-dev-6-proj-2",
            "description": "API wrapper",
            "stars": 1142,
            "language": "JavaScript"
          }
        ],
        "twitterUsername": null,
        "blog": null
      },
      {
        "login": "eth-dev-7",
        "avatarUrl": "https://avatars.githubusercontent.com/u/42006?v=4",
        "name": "Dev 7 (Ethiopia)",
        "company": "Amazon",
        "location": "Ethiopia",
        "bio": null,
        "followers": 3962,
        "publicContributions": 27624,
        "privateContributions": 273,
        "languages": ["Rust"],
        "topRepos": [
          {
            "name": "eth-dev-7-proj-1",
            "description": "Data pipeline library",
            "stars": 568,
            "language": "Rust"
          },
          {
            "name": "eth-dev-7-proj-2",
            "description": "Open source utilities",
            "stars": 864,
            "language": "Rust"
          },
          {
            "name": "eth-dev-7-proj-3",
            "description": "API wrapper",
            "stars": 1333,
            "language": "Rust"
          }
        ],
        "twitterUsername": null,
        "blog": null
      },
      {
        "login": "eth-dev-8",
        "avatarUrl": "https://avatars.githubusercontent.com/u/42007?v=4",
        "name": "Dev 8 (Ethiopia)",
        "company": null,
        "location": "Addis ababa",
        "bio": null,
        "followers": 3803,
        "publicContributions": 26608,
        "privateContributions": 324,
        "languages": ["Go"],
        "topRepos": [
          {
            "name": "eth-dev-8-proj-1",
            "description": "A modern CLI tool",
            "stars": 1177,
            "language": "Go"
          },
          {
            "name": "eth-dev-8-proj-2",
            "description": "A modern CLI tool",
            "stars": 573,
            "language": "Go"
          }
        ],
        "twitterUsername": null,
        "blog": null
      },
      {
        "login": "eth-dev-9",
        "avatarUrl": "https://avatars.githubusercontent.com/u/42008?v=4",
        "name": "Dev 9 (Ethiopia)",
        "company": "Stripe",
        "location": "Ethiopia",
        "bio": null,
        "followers": 3663,
        "publicContributions": 25489,
        "privateContributions": 70,
        "languages": ["TypeScript", "JavaScript", "Python", "PHP"],
        "topRepos": [
          {
            "name": "eth-dev-9-proj-1",
            "description": null,
            "stars": 458,
            "language": "TypeScript"
          },
          {
            "name": "eth-dev-9-proj-2",
            "description": "Open source utilities",
            "stars": 256,
            "language": "JavaScript"
          }
        ],
        "twitterUsername": null,
        "blog": null
      },
      {
        "login": "eth-dev-10",
        "avatarUrl": "https://avatars.githubusercontent.com/u/42009?v=4",
        "name": "Dev 10 (Ethiopia)",
        "company": "Google",
        "location": "Ethiopia",
        "bio": null,
        "followers": 3512,
        "publicContributions": 24516,
        "privateContributions": 422,
        "languages": ["Go"],
        "topRepos": [
          {
            "name": "eth-dev-10-proj-1",
            "description": null,
            "stars": 928,
            "language": "Go"
          }
        ],
        "twitterUsername": null,
        "blog": null
      }
    ],
    "followers": [
      {
        "login": "eth-dev-1",
        "avatarUrl": "https://avatars.githubusercontent.com/u/42000?v=4",
        "name": "Dev 1 (Ethiopia)",
        "company": "Google",
        "location": "Addis ababa",
        "bio": "Developer from Ethiopia",
        "followers": 5010,
        "publicContributions": 35056,
        "privateContributions": 352,
        "languages": ["Kotlin", "Java"],
        "topRepos": [
          {
            "name": "eth-dev-1-proj-1",
            "description": null,
            "stars": 35,
            "language": "Kotlin"
          },
          {
            "name": "eth-dev-1-proj-2",
            "description": "Open source utilities",
            "stars": 1156,
            "language": "Java"
          }
        ],
        "twitterUsername": "eth-dev-1",
        "blog": "https://eth-dev-1.dev"
      },
      {
        "login": "eth-dev-2",
        "avatarUrl": "https://avatars.githubusercontent.com/u/42001?v=4",
        "name": "Dev 2 (Ethiopia)",
        "company": "Microsoft",
        "location": "Ethiopia",
        "bio": "Developer from Ethiopia",
        "followers": 4837,
        "publicContributions": 33756,
        "privateContributions": 362,
        "languages": ["TypeScript", "Python"],
        "topRepos": [
          {
            "name": "eth-dev-2-proj-1",
            "description": "Web framework for developers",
            "stars": 1879,
            "language": "TypeScript"
          },
          {
            "name": "eth-dev-2-proj-2",
            "description": "Data pipeline library",
            "stars": 1368,
            "language": "Python"
          }
        ],
        "twitterUsername": "eth-dev-2",
        "blog": null
      },
      {
        "login": "eth-dev-3",
        "avatarUrl": "https://avatars.githubusercontent.com/u/42002?v=4",
        "name": "Dev 3 (Ethiopia)",
        "company": "Apple",
        "location": "Ethiopia",
        "bio": "Developer from Ethiopia",
        "followers": 4659,
        "publicContributions": 32392,
        "privateContributions": 240,
        "languages": ["Swift"],
        "topRepos": [
          {
            "name": "eth-dev-3-proj-1",
            "description": "Data pipeline library",
            "stars": 1131,
            "language": "Swift"
          },
          {
            "name": "eth-dev-3-proj-2",
            "description": "Open source utilities",
            "stars": 397,
            "language": "Swift"
          }
        ],
        "twitterUsername": null,
        "blog": null
      },
      {
        "login": "eth-dev-4",
        "avatarUrl": "https://avatars.githubusercontent.com/u/42003?v=4",
        "name": "Dev 4 (Ethiopia)",
        "company": "Amazon",
        "location": "Ethiopia",
        "bio": null,
        "followers": 4452,
        "publicContributions": 31181,
        "privateContributions": 202,
        "languages": ["Java", "Go", "C++", "Swift"],
        "topRepos": [
          {
            "name": "eth-dev-4-proj-1",
            "description": "A modern CLI tool",
            "stars": 1216,
            "language": "Java"
          },
          {
            "name": "eth-dev-4-proj-2",
            "description": "Data pipeline library",
            "stars": 595,
            "language": "Go"
          },
          {
            "name": "eth-dev-4-proj-3",
            "description": "Web framework for developers",
            "stars": 598,
            "language": "C++"
          }
        ],
        "twitterUsername": null,
        "blog": null
      },
      {
        "login": "eth-dev-5",
        "avatarUrl": "https://avatars.githubusercontent.com/u/42004?v=4",
        "name": "Dev 5 (Ethiopia)",
        "company": null,
        "location": "Addis ababa",
        "bio": null,
        "followers": 4277,
        "publicContributions": 30001,
        "privateContributions": 258,
        "languages": ["Java", "Python", "Rust"],
        "topRepos": [
          {
            "name": "eth-dev-5-proj-1",
            "description": "Open source utilities",
            "stars": 997,
            "language": "Java"
          },
          {
            "name": "eth-dev-5-proj-2",
            "description": null,
            "stars": 877,
            "language": "Python"
          }
        ],
        "twitterUsername": null,
        "blog": null
      },
      {
        "login": "eth-dev-6",
        "avatarUrl": "https://avatars.githubusercontent.com/u/42005?v=4",
        "name": "Dev 6 (Ethiopia)",
        "company": "GitHub",
        "location": "Ethiopia",
        "bio": null,
        "followers": 4105,
        "publicContributions": 28812,
        "privateContributions": 205,
        "languages": ["JavaScript"],
        "topRepos": [
          {
            "name": "eth-dev-6-proj-1",
            "description": null,
            "stars": 987,
            "language": "JavaScript"
          },
          {
            "name": "eth-dev-6-proj-2",
            "description": "API wrapper",
            "stars": 1142,
            "language": "JavaScript"
          }
        ],
        "twitterUsername": null,
        "blog": null
      },
      {
        "login": "eth-dev-7",
        "avatarUrl": "https://avatars.githubusercontent.com/u/42006?v=4",
        "name": "Dev 7 (Ethiopia)",
        "company": "Amazon",
        "location": "Ethiopia",
        "bio": null,
        "followers": 3962,
        "publicContributions": 27624,
        "privateContributions": 273,
        "languages": ["Rust"],
        "topRepos": [
          {
            "name": "eth-dev-7-proj-1",
            "description": "Data pipeline library",
            "stars": 568,
            "language": "Rust"
          },
          {
            "name": "eth-dev-7-proj-2",
            "description": "Open source utilities",
            "stars": 864,
            "language": "Rust"
          },
          {
            "name": "eth-dev-7-proj-3",
            "description": "API wrapper",
            "stars": 1333,
            "language": "Rust"
          }
        ],
        "twitterUsername": null,
        "blog": null
      },
      {
        "login": "eth-dev-8",
        "avatarUrl": "https://avatars.githubusercontent.com/u/42007?v=4",
        "name": "Dev 8 (Ethiopia)",
        "company": null,
        "location": "Addis ababa",
        "bio": null,
        "followers": 3803,
        "publicContributions": 26608,
        "privateContributions": 324,
        "languages": ["Go"],
        "topRepos": [
          {
            "name": "eth-dev-8-proj-1",
            "description": "A modern CLI tool",
            "stars": 1177,
            "language": "Go"
          },
          {
            "name": "eth-dev-8-proj-2",
            "description": "A modern CLI tool",
            "stars": 573,
            "language": "Go"
          }
        ],
        "twitterUsername": null,
        "blog": null
      },
      {
        "login": "eth-dev-9",
        "avatarUrl": "https://avatars.githubusercontent.com/u/42008?v=4",
        "name": "Dev 9 (Ethiopia)",
        "company": "Stripe",
        "location": "Ethiopia",
        "bio": null,
        "followers": 3663,
        "publicContributions": 25489,
        "privateContributions": 70,
        "languages": ["TypeScript", "JavaScript", "Python", "PHP"],
        "topRepos": [
          {
            "name": "eth-dev-9-proj-1",
            "description": null,
            "stars": 458,
            "language": "TypeScript"
          },
          {
            "name": "eth-dev-9-proj-2",
            "description": "Open source utilities",
            "stars": 256,
            "language": "JavaScript"
          }
        ],
        "twitterUsername": null,
        "blog": null
      },
      {
        "login": "eth-dev-10",
        "avatarUrl": "https://avatars.githubusercontent.com/u/42009?v=4",
        "name": "Dev 10 (Ethiopia)",
        "company": "Google",
        "location": "Ethiopia",
        "bio": null,
        "followers": 3512,
        "publicContributions": 24516,
        "privateContributions": 422,
        "languages": ["Go"],
        "topRepos": [
          {
            "name": "eth-dev-10-proj-1",
            "description": null,
            "stars": 928,
            "language": "Go"
          }
        ],
        "twitterUsername": null,
        "blog": null
      }
    ]
  }
}
